aws_s3sync/__init__.py
aws_s3sync-1.0.1.dist-info/DESCRIPTION.rst
aws_s3sync-1.0.1.dist-info/METADATA
aws_s3sync-1.0.1.dist-info/RECORD
aws_s3sync-1.0.1.dist-info/WHEEL
aws_s3sync-1.0.1.dist-info/entry_points.txt
aws_s3sync-1.0.1.dist-info/metadata.json
aws_s3sync-1.0.1.dist-info/top_level.txt
