Metadata-Version: 2.0
Name: aws-s3sync
Version: 1.0.1
Summary: A utility to sync data to/from AWS S3
Home-page: https://github.com/mikhailadvani/s3sync
Author: Mikhail Advani
Author-email: mikhail.advani@gmail.com
License: Apache
Keywords: aws s3
Platform: UNKNOWN
Classifier: Development Status :: 2 - Pre-Alpha
Classifier: Intended Audience :: Developers
Classifier: Intended Audience :: System Administrators
Classifier: Topic :: System :: Archiving :: Mirroring
Classifier: License :: OSI Approved :: Apache Software License
Classifier: Programming Language :: Python :: 2.7
Requires-Dist: boto
Provides-Extra: dev
Requires-Dist: twine; extra == 'dev'
